paddle_ner/__init__.py
paddle_ner/data_reader.py
paddle_ner/server.py
paddle_ner/train.py
paddle_ner-0.1.0.dist-info/LICENSE
paddle_ner-0.1.0.dist-info/METADATA
paddle_ner-0.1.0.dist-info/WHEEL
paddle_ner-0.1.0.dist-info/top_level.txt
paddle_ner-0.1.0.dist-info/RECORD
