Metadata-Version: 2.1
Name: paddle-ner
Version: 0.1.0
Summary: A NER extractor write in PaddlePaddle
Home-page: https://github.com/howlandersonn/PaddleNER
Author: Xiaoquan Kong
Author-email: u1mail2me@gmail.com
License: AGPL license
Keywords: paddle_ner
Platform: UNKNOWN
Classifier: Development Status :: 2 - Pre-Alpha
Classifier: Intended Audience :: Developers
Classifier: License :: OSI Approved :: MIT License
Classifier: Natural Language :: English
Classifier: Programming Language :: Python :: 2
Classifier: Programming Language :: Python :: 2.7
Classifier: Programming Language :: Python :: 3
Classifier: Programming Language :: Python :: 3.5
Classifier: Programming Language :: Python :: 3.6
Classifier: Programming Language :: Python :: 3.7
Requires-Dist: paddlepaddle (<2.0)
Requires-Dist: tokenizer-tools
Requires-Dist: flask
Requires-Dist: Flask-Cors
